nuwa_build/__init__.py
nuwa_build/backend.py
nuwa_build/cleanup.py
nuwa_build/cli.py
nuwa_build/config.py
nuwa_build/discovery.py
nuwa_build/errors.py
nuwa_build/magic.py
nuwa_build/pep517_hooks.py
nuwa_build/scaffolding.py
nuwa_build/stubs.py
nuwa_build/templates.py
nuwa_build/utils.py
nuwa_build/watch.py
nuwa_build-0.3.6.dist-info/licenses/LICENSE
nuwa_build-0.3.6.dist-info/METADATA
nuwa_build-0.3.6.dist-info/WHEEL
nuwa_build-0.3.6.dist-info/entry_points.txt
nuwa_build-0.3.6.dist-info/top_level.txt
nuwa_build-0.3.6.dist-info/RECORD
