Metadata-Version: 2.4
Name: nuwa-build
Version: 0.3.6
Summary: Build and publish Nim extensions for Python with zero configuration.
Author-email: Martin Eastwood <martin.eastwood@gmx.com>
License: MIT
Classifier: Development Status :: 4 - Beta
Classifier: Intended Audience :: Developers
Classifier: Programming Language :: Python :: 3
Classifier: Programming Language :: Python :: 3.9
Classifier: Programming Language :: Python :: 3.10
Classifier: Programming Language :: Python :: 3.11
Classifier: Programming Language :: Python :: 3.12
Classifier: Programming Language :: Python :: 3.13
Classifier: Programming Language :: Python :: 3.14
Classifier: Topic :: Software Development :: Build Tools
Requires-Python: >=3.9
License-File: LICENSE
Requires-Dist: ipython>=7.0.0
Requires-Dist: packaging>=23.0
Requires-Dist: tomli>=1.2.0; python_version < "3.11"
Requires-Dist: watchdog>=5.0.0
Requires-Dist: wheel>=0.40.0
Provides-Extra: test
Requires-Dist: pytest>=7.0.0; extra == "test"
Requires-Dist: pytest-cov>=4.0.0; extra == "test"
Provides-Extra: dev
Requires-Dist: mypy>=1.0.0; extra == "dev"
Requires-Dist: ruff>=0.1.0; extra == "dev"
Requires-Dist: pre-commit>=4.0.0; extra == "dev"
Dynamic: license-file
